baclib/__init__.py
baclib/alignment.py
baclib/external.py
baclib/genome.py
baclib/graph.py
baclib/io.py
baclib/seq.py
baclib/utils.py
baclib-1.0.0a1.dist-info/METADATA
baclib-1.0.0a1.dist-info/WHEEL
baclib-1.0.0a1.dist-info/licenses/LICENSE
baclib-1.0.0a1.dist-info/RECORD
