Metadata-Version: 2.4
Name: baclib
Version: 1.0.0a1
Summary: Lightweight Python Library for Bacterial Genomics
Author-email: Tom Stanton <tomdstanton@gmail.com>
License:                     GNU GENERAL PUBLIC LICENSE
License-File: LICENSE
Keywords: bioinformatics,genomics,microbiology
Classifier: Environment :: Console
Classifier: License :: OSI Approved :: GNU General Public License v3 (GPLv3)
Classifier: Operating System :: OS Independent
Classifier: Programming Language :: Python :: 3.11
Classifier: Programming Language :: Python :: 3.12
Classifier: Programming Language :: Python :: 3.13
Classifier: Programming Language :: Python :: 3.14
Classifier: Topic :: Scientific/Engineering :: Bio-Informatics
Classifier: Topic :: Scientific/Engineering :: Medical Science Apps.
Requires-Python: >=3.11
Requires-Dist: numpy
Requires-Dist: scipy
Provides-Extra: docs
Requires-Dist: mkdocs-api-autonav; extra == 'docs'
Requires-Dist: mkdocs-include-markdown-plugin; extra == 'docs'
Requires-Dist: mkdocs-material; extra == 'docs'
Provides-Extra: test
Requires-Dist: pytest; extra == 'test'
